{
    "maps": [
        {
            "name": "Tutorial",
            "background": "tutorial.jpg",
            "ground_height": 0.450,
        
            "characters": [
                {"name": "Mario","xPosition": 100, "text": "Hello there"},
                {"name": "RedToad", "xPosition": 200},
                {"name": "HammerBros","xPosition": 300}
            ],
            
            "connections": [
                {"East": [{"x_border_position": -10, "destination": "Hub"}]}
        ]},

        {
            "name": "Hub",
            "background": "hub.jpg",
            "ground_height": 0.450,

            "characters": [
                {"name": "Mario","xPosition": 50},
                {"name": "RedToad","xPosition": 50, "text": "Welcome to the hub."},
                {"name": "RedToad","xPosition": 100, "text": "Oh Mario !!!! The real one ?!."},
                {"name": "RedToad","xPosition": 200, "text": "Hate you."}
            ],

            "connections": [
                {"East": [{"x_border_position": 10, "destination": "Tutorial"}]},  
                {"West": [{"x_border_position": -10, "destination": "FirstStage"}]}  
            ]
        }
    ]
}
